{
	"instance" : {
		"gtInspectorHotTracesIn:" : "LukeGorrie 11/23/2017 15:24",
		"mcode" : "LukeGorrie 11/24/2017 09:07",
		"total" : "LukeGorrie 11/24/2017 09:25",
		"vmPercent" : "LukeGorrie 11/24/2017 09:25",
		"name" : "LukeGorrie 8/1/2017 10:12",
		"process:" : "LukeGorrie 8/1/2017 16:16",
		"process" : "LukeGorrie 8/1/2017 16:16",
		"name:" : "LukeGorrie 8/1/2017 11:36",
		"gc" : "LukeGorrie 11/24/2017 09:07",
		"gcPercent" : "LukeGorrie 11/24/2017 09:26",
		"loadFromFileNamed:" : "LukeGorrie 11/22/2017 13:13",
		"trace:" : "LukeGorrie 11/24/2017 11:20",
		"vm" : "LukeGorrie 11/24/2017 09:07",
		"locations" : "LukeGorrie 12/5/2017 13:15",
		"mcodePercent" : "LukeGorrie 11/24/2017 09:26"
	},
	"class" : {
		"loadFromFileNamed:name:process:" : "LukeGorrie 8/1/2017 16:17"
	}
}